{
  "Footer": {
    "description": "Auto imported from components/global/Footer.vue"
  },
  "Header": {
    "description": "Auto imported from components/global/Header.vue"
  },
  "Modal": {
    "description": "Auto imported from components/global/Modal.vue"
  },
  "ComiteProfile": {
    "description": "Auto imported from components/comite/Profile.vue"
  },
  "HomeBenefits": {
    "description": "Auto imported from components/home/Benefits.vue"
  },
  "HomeConvene": {
    "description": "Auto imported from components/home/Convene.vue"
  },
  "HomeGoals": {
    "description": "Auto imported from components/home/Goals.vue"
  },
  "HomeHero": {
    "description": "Auto imported from components/home/Hero.vue"
  },
  "HomeInterest": {
    "description": "Auto imported from components/home/Interest.vue"
  },
  "HomeSpeakers": {
    "description": "Auto imported from components/home/Speakers.vue"
  },
  "HomeTag": {
    "description": "Auto imported from components/home/Tag.vue"
  }
}
